{
  "_fv": 43,
  "_type": "recipe",
  "definition": {
    "recipeType": "Crafting",
    "recipeRetstackSize": 1,
    "group": "",
    "cookingBookCategory": "MISC",
    "xpReward": 0.0,
    "cookingTime": 200,
    "craftingBookCategory": "MISC",
    "recipeShapeless": false,
    "recipeSlots": [
      {
        "value": ""
      },
      {
        "value": "CUSTOM:Literiumingot"
      },
      {
        "value": ""
      },
      {
        "value": ""
      },
      {
        "value": "CUSTOM:Literiumingot"
      },
      {
        "value": ""
      },
      {
        "value": "CUSTOM:AncientRemains"
      },
      {
        "value": "Items.STICK"
      },
      {
        "value": "CUSTOM:AncientRemains"
      }
    ],
    "recipeReturnStack": {
      "value": "CUSTOM:TestSword"
    },
    "name": "test_swordrecipe",
    "namespace": "mod"
  }
}