{
  "type": "minecraft:crafting_shaped",
  "pattern": [
    " 1 ",
    "3 5",
    "6 8"
  ],
  "key": {
    "1": {
      "item": "ancient_ruins:ancient_remains"
    },
    "3": {
      "item": "ancient_ruins:literiumingot"
    },
    "5": {
      "item": "ancient_ruins:literiumingot"
    },
    "6": {
      "item": "ancient_ruins:literiumingot"
    },
    "8": {
      "item": "ancient_ruins:literiumingot"
    }
  },
  "result": {
    "item": "ancient_ruins:literium_armor_boots",
    "count": 1
  }
}